{"nodes": [{"id": "c_users_cs05180_documents_hotel_price_checker_scratch_rename_invoices_py", "label": "rename_invoices.py", "file_type": "code", "source_file": "C:\\Users\\CS05180\\Documents\\hotel-price-checker\\scratch\\rename_invoices.py", "source_location": "L1"}], "edges": [{"source": "c_users_cs05180_documents_hotel_price_checker_scratch_rename_invoices_py", "target": "os", "relation": "imports", "context": "import", "confidence": "EXTRACTED", "source_file": "C:\\Users\\CS05180\\Documents\\hotel-price-checker\\scratch\\rename_invoices.py", "source_location": "L1", "weight": 1.0}, {"source": "c_users_cs05180_documents_hotel_price_checker_scratch_rename_invoices_py", "target": "shutil", "relation": "imports", "context": "import", "confidence": "EXTRACTED", "source_file": "C:\\Users\\CS05180\\Documents\\hotel-price-checker\\scratch\\rename_invoices.py", "source_location": "L2", "weight": 1.0}, {"source": "c_users_cs05180_documents_hotel_price_checker_scratch_rename_invoices_py", "target": "pandas", "relation": "imports", "context": "import", "confidence": "EXTRACTED", "source_file": "C:\\Users\\CS05180\\Documents\\hotel-price-checker\\scratch\\rename_invoices.py", "source_location": "L3", "weight": 1.0}], "raw_calls": []}